django_logger/__init__.py
django_logger/decorator.py
django_logger/log_handler.py
django_logger/logformat.py
django_logger/settings.py
easy_django_logger-0.1.1.dist-info/LICENSE
easy_django_logger-0.1.1.dist-info/METADATA
easy_django_logger-0.1.1.dist-info/WHEEL
easy_django_logger-0.1.1.dist-info/top_level.txt
easy_django_logger-0.1.1.dist-info/RECORD
