Metadata-Version: 2.1
Name: easy-django-logger
Version: 0.1.1
Summary: Django logger to log formatted logs parsable via elastic search and visualize via kibana.
Home-page: https://github.com/NiranjanSingh/django-logger
Author: Niranjan Singh
Author-email: niranjan32331@gmail.com
License: MIT
Platform: UNKNOWN
Requires-Dist: Django (<2,>=1.8)
Requires-Dist: arrow (>=0.12.1)
Requires-Dist: pytz (>=2017.3)
